<?xml version="1.0" encoding="UTF-8"?>
<schemalist gettext-domain="0dyseus@WallpaperChangerApplet">
    <schema id="org.cinnamon.applets.0dyseus@WallpaperChangerApplet" path="/org/cinnamon/applets/0dyseus@WallpaperChangerApplet/">
        <key type="b" name="auto-rotate">
            <default>true</default>
            <description>
                When enabled, this will cause the daemon to automatically change the wallpaper whenever the current profile is changed.
            </description>
            <summary>Auto rotate wallpaper when the profile is changed.</summary>
        </key>
        <key type="b" name="auto-start">
            <default>false</default>
            <description>
                When enabled, the daemon will be automatically started when the applet is loaded. If it is already running or this is disabled, no action will be taken.
            </description>
            <summary>Automatically start the daemon when the applet loads</summary>
        </key>
        <key type="s" name="current-profile">
            <default>"Cinnamon"</default>
            <description>
                This is the current profile that the daemon will load.
            </description>
            <summary>Currently loaded profile</summary>
        </key>
        <key type="i" name="interval">
            <default>10</default>
            <description>
                When timer is enabled, the interval is the amount of time in seconds between the daemon switching the wallpaper to the next available wallpaper. Default is 10 seconds.
            </description>
            <summary>Number of seconds between wallpaper changes</summary>
        </key>
        <key type="as" name="next-wallpaper-shortcut">
            <default>
                <![CDATA[['']]]>
            </default>
            <description>
                Keyboard shortcut to cause the daemon to display the next wallpaper.
            </description>
            <summary>Change to next wallpaper</summary>
        </key>
        <key type="b" name="notifications">
            <default>true</default>
            <description>
                Display a notification each time an event happens with wallpaper changer. This does not stop the applet from reporting errors.
            </description>
            <summary>Display notifications with the applet</summary>
        </key>
        <key type="as" name="prev-wallpaper-shortcut">
            <default>
                <![CDATA[['']]]>
            </default>
            <description>
                Keyboard shortcut to cause the daemon to display the previous wallpaper.
            </description>
            <summary>Change to previous wallpaper</summary>
        </key>
        <key type="a{sa(sb)}" name="profiles">
            <default>[{"Cinnamon",[("file:///usr/share/backgrounds", true)]}]</default>
            <description>
                These are all the available profiles. By default it contains a single profile that will recursively load /usr/share/backgrouds
            </description>
            <summary>All currently available profiles</summary>
        </key>
        <key type="a{s(ss)}" name="profile-state">
            <default>[]</default>
            <description>
                This is the storage location of the profile's last state. By default, there are no states saved until a new profile is loaded.
            </description>
            <summary>Profile's last saved state</summary>
        </key>
        <key type="b" name="random">
            <default>false</default>
            <description>
                If set to true the daemon will randomize the order in which the wallpapers are displayed
            </description>
            <summary>Display wallpapers in a random order</summary>
        </key>
        <key type="b" name="remember-profile-state">
            <default>false</default>
            <description>
                When enabled, the daemon will remember its current and next wallpaper for the current profile when the profile is changed. This means returning back to the profile will restore the previous background plus the next in queue.
            </description>
            <summary>Remember profile last wallpaper on load</summary>
        </key>
        <key type="s" name="rotation">
            <choices>
                <choice value="disabled"></choice>
                <choice value="hourly"></choice>
                <choice value="interval"></choice>
            </choices>
            <default>"interval"</default>
            <description>
                Choose how the rotation is handled by the daemon. The interval choice is the default. It enables a timer that uses the interval value to change the wallpaper every [interval] seconds. For hourly, the wallpaper will be changed at the beginning of every hour of the day. When disabled, rotation is not done by the daemon, but only by user interaction with the applet.
            </description>
            <summary>Different options to control when the wallpaper is changed</summary>
        </key>
        <key type="s" name="custom-applet-label">
            <default>""</default>
        </key>
        <key type="s" name="custom-applet-icon">
            <default>"image-x-generic-symbolic"</default>
        </key>
        <key type="b" name="daemon-is-running">
            <default>false</default>
        </key>
        <key type="b" name="toggle-daemon">
            <default>false</default>
        </key>
        <key type="b" name="logging-enabled">
            <default>false</default>
        </key>
        <key type="b" name="invert-menu-items-order">
            <default>false</default>
        </key>
        <key type="i" name="wallpaper-preview-width">
            <default>220</default>
        </key>
        <key type="as" name="toggle-menu-shortcut">
            <default>
                <![CDATA[['']]]>
            </default>
        </key>
        <key type="b" name="window-remember-size">
            <default>true</default>
        </key>
        <key type="i" name="window-width">
            <default>720</default>
        </key>
        <key type="i" name="window-height">
            <default>420</default>
        </key>
    </schema>
</schemalist>
