{"regions":{"kz":[{"k":"f","d":1,"m":1,"c":null,"n":"Жаңа жыл","p":true},{"k":"f","d":8,"m":3,"c":null,"n":"Халықаралық әйелдер күні","p":true},{"k":"f","d":22,"m":3,"c":null,"n":"Наурыз мейрамы","p":true},{"k":"f","d":1,"m":5,"c":null,"n":"Қазақстан халқының бірлігі мерекесі","p":true},{"k":"f","d":7,"m":5,"c":null,"n":"Отан қорғаушы күні","p":false},{"k":"f","d":9,"m":5,"c":null,"n":"Жеңіс күні","p":true},{"k":"f","d":6,"m":7,"c":null,"n":"Астана күні","p":true},{"k":"f","d":30,"m":8,"c":null,"n":"Қазақстан Республикасының Конституциясы күні","p":true},{"k":"f","d":16,"m":12,"c":null,"n":"Тәуелсіздік күні","p":true},{"k":"unknown","raw":"hijri thualhijjah 10","n":"Құрбан айттың бірінші күні","p":true},{"k":"f","d":7,"m":1,"c":null,"n":"Православиелік Рождество","p":true},{"k":"f","d":21,"m":1,"c":null,"n":"Инженерлiк әскерлер күнi","p":false},{"k":"f","d":27,"m":2,"c":null,"n":"Хатшылар күнi","p":false},{"k":"f","d":16,"m":3,"c":null,"n":"Республикалық ұлан күнi","p":false},{"k":"f","d":18,"m":3,"c":null,"n":"Сауда күнi","p":false},{"k":"f","d":27,"m":3,"c":null,"n":"Театр күнi","p":false},{"k":"f","d":1,"m":4,"c":null,"n":"Геолог күнi","p":false},{"k":"f","d":1,"m":4,"c":null,"n":"Күлкi күнi","p":false},{"k":"f","d":2,"m":4,"c":null,"n":"Қазақстан Республикасы әскери-теңiз күштерi күнi","p":false},{"k":"f","d":6,"m":4,"c":null,"n":"Тергеуші күні","p":false},{"k":"f","d":12,"m":4,"c":null,"n":"Ғарышкер күні","p":false},{"k":"f","d":15,"m":4,"c":null,"n":"Әуе қорғаныс әскерлерiнiң күнi","p":false},{"k":"f","d":16,"m":4,"c":null,"n":"Ғылым күнi","p":false},{"k":"f","d":17,"m":4,"c":null,"n":"Өртке қарсы қызмет қызметкерлерiнiң күнi","p":false},{"k":"f","d":28,"m":4,"c":null,"n":"Бүкiләлемдiк еңбек қорғау күні","p":false},{"k":"f","d":29,"m":4,"c":null,"n":"Халықаралық би күнi","p":false},{"k":"f","d":5,"m":5,"c":null,"n":"Радио күні","p":false},{"k":"f","d":27,"m":5,"c":null,"n":"Химиктер күнi","p":false},{"k":"f","d":31,"m":5,"c":null,"n":"Саяси қуғын-сүргіндер құрбандарын еске","p":false},{"k":"f","d":1,"m":6,"c":null,"n":"Балаларды қорғау күнi","p":false},{"k":"f","d":4,"m":6,"c":null,"n":"Қазақстан Республикасының мемлекеттік","p":false},{"k":"f","d":5,"m":6,"c":null,"n":"Айналадағы ортаны қорғау күні","p":false},{"k":"f","d":14,"m":6,"c":null,"n":"Бүкiләлемдiк донор күнi","p":false},{"k":"f","d":23,"m":6,"c":null,"n":"Полиция күні","p":false},{"k":"r","raw":"third sunday in june","c":null,"n":"Медицина қызметкері күні","p":false},{"k":"r","raw":"last sunday in june","c":null,"n":"Баспасөз, теледидар және радио күнi","p":false},{"k":"f","d":2,"m":7,"c":null,"n":"Дипломатиялық қызмет күні","p":false},{"k":"f","d":6,"m":7,"c":null,"n":"Бүкiләлемдiк сүйісу күні","p":false},{"k":"f","d":13,"m":7,"c":null,"n":"Ұлттық қауiпсiздiк комитетiнiң күнi. Прокуратура күнi","p":false},{"k":"r","raw":"first sunday in july","c":null,"n":"Теңіз және өзен флоты күні","p":false},{"k":"r","raw":"third sunday in july","c":null,"n":"Металлург күні","p":false},{"k":"r","raw":"last friday in july","c":null,"n":"Жүйелік администратор күні","p":false},{"k":"f","d":2,"m":8,"c":null,"n":"Әуе-десант әскерлерінің күні","p":false},{"k":"f","d":18,"m":8,"c":null,"n":"Шекаралық әскерлер күнi","p":false},{"k":"f","d":19,"m":8,"c":null,"n":"Әуе флоты күнi","p":false},{"k":"r","raw":"first sunday in august","c":null,"n":"Көлік және байланыс қызметкерлері күні","p":false},{"k":"r","raw":"second sunday in august","c":null,"n":"Құрылысшы күні","p":false},{"k":"r","raw":"third sunday in august","c":null,"n":"Спорт күні","p":false},{"k":"r","raw":"last sunday in august","c":null,"n":"Шахтер күні","p":false},{"k":"f","d":1,"m":9,"c":null,"n":"Бiлiм күнi","p":false},{"k":"r","raw":"first sunday in september","c":null,"n":"Мұнай-газ кешені қызметкерлерінің күні","p":false},{"k":"r","raw":"second sunday in september","c":null,"n":"Танкистер күні","p":false},{"k":"r","raw":"third sunday in september","c":null,"n":"Қазақстан Республикасының халықтары","p":false},{"k":"f","d":28,"m":9,"c":null,"n":"Атом саласының қызметкерлері күні","p":false},{"k":"f","d":5,"m":10,"c":null,"n":"Сәулетшi күнi","p":false},{"k":"f","d":6,"m":10,"c":null,"n":"Есепшiлер және тексерушiлер күнi","p":false},{"k":"f","d":9,"m":10,"c":null,"n":"Бүкіләлемдік пошта күні","p":false},{"k":"f","d":15,"m":10,"c":null,"n":"Кiтапханашы күнi","p":false},{"k":"f","d":20,"m":10,"c":null,"n":"Байланыс қызметкерлерiнiң күнi","p":false},{"k":"f","d":28,"m":10,"c":null,"n":"Автомобиль көлiгi қызметкерлерiнiң күнi","p":false},{"k":"r","raw":"first sunday in october","c":null,"n":"Мұғалiм күнi","p":false},{"k":"f","d":15,"m":11,"c":null,"n":"Ұлттық валюта күні","p":false},{"k":"f","d":17,"m":11,"c":null,"n":"Студенттер күнi","p":false},{"k":"f","d":17,"m":11,"c":null,"n":"Ракета әскерлері және артиллерия күнi","p":false},{"k":"f","d":23,"m":11,"c":null,"n":"Жол полициясы қызметкерлерiнiң күнi","p":false},{"k":"r","raw":"third sunday in november","c":null,"n":"Ауыл шаруашылығы қызметкерлерінің күні","p":false},{"k":"f","d":12,"m":12,"c":null,"n":"Қазақстан Республикасы кеден қызметiнiң күнi","p":false},{"k":"f","d":25,"m":12,"c":null,"n":"Экономист күнi","p":false},{"k":"r","raw":"third sunday in december","c":null,"n":"Энергетик күні","p":false},{"k":"f","d":23,"m":4,"c":"year>=2025","n":"Ұлттық кітап күні","p":false}]}}